skaltuchet/__init__.py
skaltuchet/__main__.py
skaltuchet-0.1.0.dist-info/METADATA
skaltuchet-0.1.0.dist-info/WHEEL
skaltuchet-0.1.0.dist-info/entry_points.txt
skaltuchet-0.1.0.dist-info/top_level.txt
skaltuchet-0.1.0.dist-info/RECORD
