Metadata-Version: 2.1
Name: skaltuchet
Version: 0.1.0
Summary: A hilarious fake hacking script to prank your friends!
Home-page: https://github.com/skaltuch
Author: skaltuchet
Classifier: Programming Language :: Python :: 3
Classifier: License :: OSI Approved :: MIT License
Classifier: Operating System :: OS Independent
Requires-Python: >=3.6
